Metadata-Version: 2.1
Name: latest-earthquake-bmkg
Version: 0.6
Summary: This package will get latest earthquake from BMKG | Meteorological, Climatological, and Geophysical Agency
Home-page: https://github.com/qaulants/latest-earthquake-Indonesia
Author: Qaulan Tsaqila
Author-email: qaulantsaqila75@gmail.com
Classifier: Programming Language :: Python :: 3
Classifier: License :: OSI Approved :: GNU General Public License v3 (GPLv3)
Classifier: Operating System :: OS Independent
Classifier: Development Status :: 5 - Production/Stable
Requires-Python: >=3.6
License-File: LICENSE
